molecule_kubevirt/__init__.py
molecule_kubevirt/driver.py
molecule_kubevirt/cookiecutter/cookiecutter.json
molecule_kubevirt/cookiecutter/{{cookiecutter.molecule_directory}}/{{cookiecutter.scenario_name}}/converge.yml
molecule_kubevirt/playbooks/create.yml
molecule_kubevirt/playbooks/destroy.yml
molecule_kubevirt/test/__init__.py
molecule_kubevirt/test/conftest.py
molecule_kubevirt/test/test_driver.py
molecule_kubevirt/test/test_init.py
molecule_kubevirt/test/test_scenario_tests.py
molecule_kubevirt/test/refs/instance-almost-default.yml
molecule_kubevirt/test/refs/instance-full.yml
molecule_kubevirt/test/refs/instance-running-false.yml
molecule_kubevirt/test/refs/user_data-instance-almost-default.yml
molecule_kubevirt/test/refs/user_data-instance-full.yml
molecule_kubevirt-0.1.0.dist-info/LICENSE
molecule_kubevirt-0.1.0.dist-info/METADATA
molecule_kubevirt-0.1.0.dist-info/WHEEL
molecule_kubevirt-0.1.0.dist-info/entry_points.txt
molecule_kubevirt-0.1.0.dist-info/top_level.txt
molecule_kubevirt-0.1.0.dist-info/RECORD
