Metadata-Version: 2.1
Name: molecule-kubevirt
Version: 0.1.0
Summary: Molecule aids in the development and testing of Ansible roles
Home-page: https://github.com/jseguillon/molecule-kubevirt
Author: Joël Séguillon
Author-email: joel.seguillon@gmail.com
Maintainer: Joël Séguillon
Maintainer-email: joel.seguillon@gmail.com
License: MIT
Project-URL: Bug Tracker, https://github.com/jseguillon/molecule-kubevirt/issues
Project-URL: Release Management, https://github.com/jseguillon/molecule-kubevirt/releases
Project-URL: CI, https://github.com/jseguillon/molecule-kubevirt/actions
Project-URL: Code of Conduct, https://docs.ansible.com/ansible/latest/community/code_of_conduct.html
Project-URL: Documentation, https://molecule.readthedocs.io
Project-URL: Discussions, https://github.com/ansible-community/molecule/discussions
Project-URL: Source Code, https://github.com/jseguillon/molecule-kubevirt
Keywords: ansible,kubevirt,testing,molecule
Platform: UNKNOWN
Classifier: Development Status :: 3 - Alpha
Classifier: Environment :: Console
Classifier: Intended Audience :: Developers
Classifier: Intended Audience :: Information Technology
Classifier: Intended Audience :: System Administrators
Classifier: License :: OSI Approved :: MIT License
Classifier: Natural Language :: English
Classifier: Operating System :: OS Independent
Classifier: Programming Language :: Python :: 3
Classifier: Programming Language :: Python :: 3.6
Classifier: Programming Language :: Python :: 3.7
Classifier: Programming Language :: Python :: 3.8
Classifier: Programming Language :: Python :: 3.9
Classifier: Topic :: System :: Systems Administration
Classifier: Topic :: Utilities
Requires-Python: >=3.6
License-File: LICENSE
Requires-Dist: molecule (>=3.2.0a0)
Requires-Dist: openshift (>=0.11.0)
Requires-Dist: kubernetes (>=11.0.0)
Provides-Extra: docs
Requires-Dist: simplejson ; extra == 'docs'
Requires-Dist: Sphinx ; extra == 'docs'
Requires-Dist: sphinx-ansible-theme (>=0.2.2) ; extra == 'docs'
Provides-Extra: lint
Requires-Dist: pre-commit (>=1.21.0) ; extra == 'lint'
Provides-Extra: test
Requires-Dist: molecule[test] ; extra == 'test'
Requires-Dist: pytest-helpers-namespace ; extra == 'test'
